README.rst
setup.cfg
setup.py
./__init__.py
./channel.py
./channel.xml
./country.py
./currency.py
./fabfile.py
./lang.py
./party.py
./product.py
./product.xml
./sale.py
./tryton.cfg
./tests/__init__.py
./tests/test_party.py
./tests/test_prestashop.py
./tests/test_product.py
./tests/test_sale.py
./view/product_channel_listing_form.xml
./view/sale_channel_form.xml
./view/wizard_export_prestashop_orders_form.xml
fio_prestashop.egg-info/PKG-INFO
fio_prestashop.egg-info/SOURCES.txt
fio_prestashop.egg-info/dependency_links.txt
fio_prestashop.egg-info/entry_points.txt
fio_prestashop.egg-info/not-zip-safe
fio_prestashop.egg-info/requires.txt
fio_prestashop.egg-info/top_level.txt